perceptron/__init__.py
perceptron/perceptron.py
package_devbk007-0.0.3.dist-info/LICENSE
package_devbk007-0.0.3.dist-info/METADATA
package_devbk007-0.0.3.dist-info/WHEEL
package_devbk007-0.0.3.dist-info/top_level.txt
package_devbk007-0.0.3.dist-info/RECORD
